llama_index/readers/youtube_transcript/__init__.py
llama_index/readers/youtube_transcript/base.py
llama_index/readers/youtube_transcript/utils.py
flying_delta_readers_youtube_transcript-0.1.0.dist-info/METADATA
flying_delta_readers_youtube_transcript-0.1.0.dist-info/WHEEL
flying_delta_readers_youtube_transcript-0.1.0.dist-info/RECORD
