Metadata-Version: 2.1
Name: flying-delta-readers-youtube-transcript
Version: 0.1.0
Summary: llama-index readers youtube transcript integration
License: MIT
Author: Your Name
Author-email: you@example.com
Requires-Python: >=3.8.1,<3.12
Classifier: License :: OSI Approved :: MIT License
Classifier: Programming Language :: Python :: 3
Classifier: Programming Language :: Python :: 3.9
Classifier: Programming Language :: Python :: 3.10
Classifier: Programming Language :: Python :: 3.11
Requires-Dist: flying-delta-core (>=0.9.32,<0.10.0)
Requires-Dist: youtube-transcript-api (>=0.5.0,<0.6.0)
